specify_cli/__init__.py
specify_cli/__main__.py
specify_cli/assistants/__init__.py
specify_cli/assistants/assistant_registry.py
specify_cli/assistants/constants.py
specify_cli/assistants/injection_points.py
specify_cli/assistants/interfaces.py
specify_cli/assistants/registry.py
specify_cli/assistants/types.py
specify_cli/assistants/claude/__init__.py
specify_cli/assistants/claude/provider.py
specify_cli/assistants/claude/validator.py
specify_cli/assistants/copilot/__init__.py
specify_cli/assistants/copilot/provider.py
specify_cli/assistants/cursor/__init__.py
specify_cli/assistants/cursor/provider.py
specify_cli/assistants/gemini/__init__.py
specify_cli/assistants/gemini/provider.py
specify_cli/assistants/gemini/validator.py
specify_cli/commands/__init__.py
specify_cli/commands/add_ai/__init__.py
specify_cli/commands/add_ai/add_ai.py
specify_cli/commands/check/__init__.py
specify_cli/commands/check/check.py
specify_cli/commands/get_prompt/__init__.py
specify_cli/commands/get_prompt/get_prompt.py
specify_cli/commands/init/__init__.py
specify_cli/commands/init/init.py
specify_cli/commands/refresh_templates/__init__.py
specify_cli/commands/refresh_templates/refresh_templates.py
specify_cli/commands/run/__init__.py
specify_cli/commands/run/run.py
specify_cli/commands/update/__init__.py
specify_cli/commands/update/check.py
specify_cli/commands/update/info.py
specify_cli/commands/update/update.py
specify_cli/core/__init__.py
specify_cli/core/app.py
specify_cli/core/constants.py
specify_cli/models/__init__.py
specify_cli/models/config.py
specify_cli/models/project.py
specify_cli/models/script.py
specify_cli/models/template.py
specify_cli/models/defaults/__init__.py
specify_cli/models/defaults/branch_defaults.py
specify_cli/models/defaults/category_defaults.py
specify_cli/models/defaults/path_defaults.py
specify_cli/services/__init__.py
specify_cli/services/agent_registry/__init__.py
specify_cli/services/agent_registry/agent_registry.py
specifyx-0.3.1.dist-info/METADATA
specifyx-0.3.1.dist-info/WHEEL
specifyx-0.3.1.dist-info/entry_points.txt
specifyx-0.3.1.dist-info/licenses/LICENSE
specifyx-0.3.1.dist-info/RECORD
