Metadata-Version: 2.4
Name: specifyx
Version: 0.3.1
Summary: Enhanced spec-driven development CLI with modern architecture and Jinja2 templating
Author-email: SpecifyX Contributors <blaz@paxia.co>
License: MIT
License-File: LICENSE
Keywords: cli,development,jinja2,project-generation,spec-driven,templates,toml
Classifier: Development Status :: 4 - Beta
Classifier: Environment :: Console
Classifier: Intended Audience :: Developers
Classifier: License :: OSI Approved :: MIT License
Classifier: Programming Language :: Python :: 3
Classifier: Programming Language :: Python :: 3.11
Classifier: Programming Language :: Python :: 3.12
Classifier: Programming Language :: Python :: 3.13
Classifier: Topic :: Software Development :: Code Generators
Classifier: Topic :: Software Development :: Libraries :: Python Modules
Requires-Python: >=3.11
Requires-Dist: colorlog
Requires-Dist: dynaconf
Requires-Dist: httpx
Requires-Dist: jinja2
Requires-Dist: packaging
Requires-Dist: platformdirs
Requires-Dist: pydantic
Requires-Dist: readchar
Requires-Dist: rich
Requires-Dist: tomli-w
Requires-Dist: typer
Provides-Extra: dev
Requires-Dist: pre-commit; extra == 'dev'
Requires-Dist: pyrefly; extra == 'dev'
Requires-Dist: pytest; extra == 'dev'
Requires-Dist: pytest-asyncio; extra == 'dev'
Requires-Dist: pytest-benchmark; extra == 'dev'
Requires-Dist: pytest-cov; extra == 'dev'
Requires-Dist: ruff; extra == 'dev'
